CHANGES.rst
MANIFEST.in
Pipfile
Pipfile.lock
README.rst
setup.cfg
setup.py
docs/readthedocs-requirements.txt
docs/source/conf.py
docs/source/index.rst
docs/source/_static/empty
docs/source/_templates/empty
src/ps/__init__.py
src/ps.plone.mlstiles.egg-info/PKG-INFO
src/ps.plone.mlstiles.egg-info/SOURCES.txt
src/ps.plone.mlstiles.egg-info/dependency_links.txt
src/ps.plone.mlstiles.egg-info/entry_points.txt
src/ps.plone.mlstiles.egg-info/namespace_packages.txt
src/ps.plone.mlstiles.egg-info/not-zip-safe
src/ps.plone.mlstiles.egg-info/requires.txt
src/ps.plone.mlstiles.egg-info/top_level.txt
src/ps/plone/__init__.py
src/ps/plone/mlstiles/__init__.py
src/ps/plone/mlstiles/config.py
src/ps/plone/mlstiles/configure.zcml
src/ps/plone/mlstiles/interfaces.py
src/ps/plone/mlstiles/migrations.py
src/ps/plone/mlstiles/profiles.zcml
src/ps/plone/mlstiles/setuphandlers.py
src/ps/plone/mlstiles/testing.py
src/ps/plone/mlstiles/locales/manual.pot
src/ps/plone/mlstiles/locales/plone.pot
src/ps/plone/mlstiles/locales/ps.plone.mlstiles.pot
src/ps/plone/mlstiles/locales/ar/LC_MESSAGES/ps.plone.mlstiles.po
src/ps/plone/mlstiles/locales/cmn/LC_MESSAGES/ps.plone.mlstiles.po
src/ps/plone/mlstiles/locales/de/LC_MESSAGES/ps.plone.mlstiles.po
src/ps/plone/mlstiles/locales/es/LC_MESSAGES/ps.plone.mlstiles.po
src/ps/plone/mlstiles/locales/et/LC_MESSAGES/ps.plone.mlstiles.po
src/ps/plone/mlstiles/locales/fr/LC_MESSAGES/ps.plone.mlstiles.po
src/ps/plone/mlstiles/locales/it/LC_MESSAGES/ps.plone.mlstiles.po
src/ps/plone/mlstiles/locales/ja/LC_MESSAGES/ps.plone.mlstiles.po
src/ps/plone/mlstiles/locales/pt/LC_MESSAGES/ps.plone.mlstiles.po
src/ps/plone/mlstiles/locales/ru/LC_MESSAGES/ps.plone.mlstiles.po
src/ps/plone/mlstiles/locales/vi/LC_MESSAGES/ps.plone.mlstiles.po
src/ps/plone/mlstiles/locales/vi_VN/LC_MESSAGES/ps.plone.mlstiles.po
src/ps/plone/mlstiles/locales/zh/LC_MESSAGES/ps.plone.mlstiles.po
src/ps/plone/mlstiles/locales/zh_TW/LC_MESSAGES/ps.plone.mlstiles.po
src/ps/plone/mlstiles/profiles/plone4/browserlayer.xml
src/ps/plone/mlstiles/profiles/plone4/cssregistry.xml
src/ps/plone/mlstiles/profiles/plone4/metadata.xml
src/ps/plone/mlstiles/profiles/plone4/ps.plone.mlstiles.txt
src/ps/plone/mlstiles/profiles/plone5/browserlayer.xml
src/ps/plone/mlstiles/profiles/plone5/metadata.xml
src/ps/plone/mlstiles/profiles/plone5/ps.plone.mlstiles.txt
