Metadata-Version: 2.1
Name: ps.plone.mlstiles
Version: 1.2.1
Summary: Tiles support for the Propertyshelf MLS Plone Embedding.
Home-page: https://github.com/propertyshelf/ps.plone.mlstiles
Author: Propertyshelf, Inc.
Author-email: development@propertyshelf.com
License: GPL
Download-URL: http://pypi.python.org/pypi/ps.plone.mlstiles
Keywords: plone zope mls listing real estate
Platform: UNKNOWN
Classifier: Development Status :: 5 - Production/Stable
Classifier: Environment :: Web Environment
Classifier: Framework :: Plone
Classifier: Framework :: Plone :: 4.2
Classifier: Framework :: Plone :: 4.3
Classifier: Framework :: Plone :: 5.0
Classifier: Framework :: Plone :: 5.1
Classifier: Intended Audience :: Developers
Classifier: License :: OSI Approved :: GNU General Public License v2 (GPLv2)
Classifier: Programming Language :: Python
Classifier: Programming Language :: Python :: 2.7
Provides-Extra: test
Provides-Extra: cover
Provides-Extra: test_mosaic
Provides-Extra: mosaic
Provides-Extra: test_cover
